<?xml version="1.0" encoding="UTF-8"?>
<font fontName="numeric" genericFamily="SansSerif">
  <glyph character="1" signature="MLCCLCCLLL">
    <path style="stroke-width:0.943; clip-path:url(#clipPath1); stroke-linejoin:round; stroke-linecap:round; stroke:none;" d="M1.399 0.0 L1.097 0.0 C1.015 0.164 0.879 0.333 0.684 0.505 C0.487 0.682 0.261 0.831 0.0 0.955 L0.0 1.406 C0.145 1.351 0.307 1.271 0.49 1.164 C0.672 1.057 0.819 0.948 0.932 0.843 L0.932 3.812 L1.399 3.812 L1.399 0.0 " xmlns="http://www.w3.org/2000/svg"/>
  </glyph>
  <glyph character="0" signature="MCCCCCCCCCCCCMCCCCCCCC">
    <path style="stroke-width:0.943; clip-path:url(#clipPath1); stroke-linejoin:round; stroke-linecap:round; stroke:none;" d="M0.375 3.483 C0.584 3.743 0.872 3.875 1.238 3.875 C1.515 3.875 1.746 3.802 1.929 3.653 C2.111 3.503 2.248 3.29 2.338 3.018 C2.43 2.742 2.475 2.384 2.475 1.938 C2.475 1.562 2.447 1.263 2.39 1.04 C2.333 0.817 2.254 0.63 2.155 0.476 C2.055 0.321 1.928 0.203 1.774 0.12 C1.621 0.039 1.443 0.0 1.238 0.0 C0.961 0.0 0.733 0.071 0.55 0.22 C0.367 0.37 0.232 0.579 0.138 0.854 C0.045 1.126 0.0 1.489 0.0 1.938 C0.0 2.649 0.125 3.165 0.375 3.483 M0.72 0.656 C0.847 0.474 1.018 0.384 1.233 0.384 C1.45 0.384 1.632 0.487 1.777 0.69 C1.923 0.897 1.997 1.312 1.997 1.938 C1.997 2.558 1.923 2.974 1.777 3.183 C1.632 3.388 1.453 3.492 1.238 3.492 C1.024 3.492 0.844 3.39 0.698 3.185 C0.552 2.976 0.478 2.562 0.478 1.938 C0.478 1.313 0.559 0.886 0.72 0.656 " xmlns="http://www.w3.org/2000/svg"/>
  </glyph>
  <glyph character="3" signature="MCCCCCCCCCCCCLCCCCCCLLCCCCCCCLC">
    <path style="stroke-width:0.943; clip-path:url(#clipPath1); stroke-linejoin:round; stroke-linecap:round; stroke:none;" d="M0.377 3.582 C0.596 3.781 0.873 3.879 1.207 3.879 C1.576 3.879 1.881 3.765 2.125 3.533 C2.365 3.304 2.486 3.02 2.486 2.691 C2.486 2.442 2.424 2.242 2.299 2.078 C2.177 1.914 2.001 1.806 1.777 1.756 C1.95 1.675 2.08 1.567 2.168 1.433 C2.256 1.3 2.299 1.15 2.299 0.986 C2.299 0.812 2.254 0.65 2.161 0.496 C2.069 0.341 1.936 0.22 1.761 0.132 C1.586 0.043 1.397 0.0 1.188 0.0 C0.888 0.0 0.638 0.085 0.435 0.257 C0.233 0.429 0.104 0.671 0.048 0.984 L0.513 1.066 C0.548 0.838 0.625 0.668 0.746 0.552 C0.867 0.437 1.018 0.381 1.199 0.381 C1.382 0.381 1.531 0.437 1.647 0.55 C1.763 0.664 1.821 0.802 1.821 0.976 C1.821 1.191 1.741 1.351 1.583 1.455 C1.424 1.556 1.246 1.609 1.046 1.609 L0.971 1.603 L0.919 2.013 C1.052 1.978 1.16 1.963 1.248 1.963 C1.464 1.963 1.642 2.031 1.782 2.171 C1.923 2.309 1.991 2.486 1.991 2.701 C1.991 2.925 1.916 3.115 1.765 3.265 C1.614 3.418 1.429 3.496 1.21 3.496 C1.026 3.496 0.868 3.433 0.739 3.317 C0.61 3.201 0.52 3.009 0.466 2.748 L0.0 2.809 C0.03 3.127 0.156 3.382 0.377 3.582 " xmlns="http://www.w3.org/2000/svg"/>
  </glyph>
  <glyph character="6" signature="MCCCCCCCCCCCCCCCCCLCMCCCCCCCCC">
    <path style="stroke-width:0.943; clip-path:url(#clipPath1); stroke-linejoin:round; stroke-linecap:round; stroke:none;" d="M2.097 0.251 C1.906 0.083 1.661 0.0 1.361 0.0 C0.962 0.0 0.644 0.144 0.406 0.434 C0.135 0.768 0.0 1.302 0.0 2.036 C0.0 2.692 0.123 3.162 0.368 3.45 C0.611 3.735 0.93 3.877 1.317 3.877 C1.546 3.877 1.75 3.824 1.93 3.714 C2.109 3.606 2.25 3.45 2.352 3.244 C2.455 3.04 2.507 2.817 2.507 2.579 C2.507 2.218 2.398 1.921 2.18 1.692 C1.96 1.464 1.697 1.35 1.386 1.35 C1.207 1.35 1.037 1.39 0.875 1.473 C0.713 1.555 0.575 1.683 0.463 1.854 C0.467 1.475 0.511 1.183 0.595 0.977 C0.68 0.77 0.796 0.615 0.942 0.507 C1.055 0.425 1.186 0.382 1.333 0.382 C1.519 0.382 1.674 0.45 1.8 0.583 C1.876 0.665 1.934 0.798 1.976 0.981 L2.44 0.946 C2.402 0.649 2.287 0.419 2.097 0.251 M0.756 1.988 C0.902 1.837 1.082 1.761 1.292 1.761 C1.503 1.761 1.68 1.837 1.821 1.988 C1.96 2.139 2.031 2.347 2.031 2.608 C2.031 2.882 1.96 3.097 1.817 3.256 C1.677 3.416 1.507 3.494 1.309 3.494 C1.175 3.494 1.046 3.455 0.924 3.378 C0.8 3.303 0.705 3.19 0.639 3.042 C0.569 2.897 0.536 2.744 0.536 2.582 C0.536 2.337 0.609 2.139 0.756 1.988 " xmlns="http://www.w3.org/2000/svg"/>
  </glyph>
  <glyph character="7" signature="MCCCLCCCLLLL">
    <path style="stroke-width:0.943; clip-path:url(#clipPath1); stroke-linejoin:round; stroke-linecap:round; stroke:none;" d="M1.86 0.447 C1.623 0.718 1.401 1.048 1.19 1.44 C0.981 1.833 0.82 2.242 0.707 2.664 C0.595 3.089 0.536 3.449 0.531 3.749 L1.01 3.749 C1.037 3.369 1.096 3.022 1.189 2.703 C1.319 2.253 1.503 1.815 1.74 1.388 C1.977 0.962 2.217 0.619 2.458 0.361 L2.458 0.0 L0.0 0.0 L0.0 0.447 L1.86 0.447 " xmlns="http://www.w3.org/2000/svg"/>
  </glyph>
  <glyph character="8" signature="MCCCCCCCCCCCCCCCCMCCCCCCCCMCCCCCCCCC">
    <path style="stroke-width:0.943; clip-path:url(#clipPath1); stroke-linejoin:round; stroke-linecap:round; stroke:none;" d="M0.188 2.095 C0.063 2.261 0.0 2.468 0.0 2.714 C0.0 3.046 0.115 3.324 0.345 3.544 C0.575 3.766 0.877 3.878 1.251 3.878 C1.627 3.878 1.928 3.768 2.158 3.546 C2.388 3.326 2.503 3.053 2.503 2.729 C2.503 2.494 2.442 2.292 2.32 2.122 C2.197 1.951 2.02 1.829 1.788 1.753 C1.977 1.684 2.115 1.583 2.209 1.451 C2.3 1.322 2.347 1.169 2.347 0.992 C2.347 0.714 2.247 0.482 2.044 0.29 C1.842 0.096 1.576 0.0 1.244 0.0 C0.914 0.0 0.65 0.094 0.451 0.283 C0.253 0.471 0.153 0.703 0.153 0.979 C0.153 1.163 0.199 1.319 0.292 1.451 C0.386 1.583 0.529 1.684 0.723 1.753 C0.492 1.815 0.313 1.928 0.188 2.095 M0.805 0.555 C0.924 0.44 1.072 0.384 1.249 0.384 C1.425 0.384 1.572 0.441 1.69 0.557 C1.809 0.675 1.869 0.819 1.869 0.99 C1.869 1.154 1.809 1.292 1.696 1.404 C1.582 1.518 1.434 1.574 1.253 1.574 C1.07 1.574 0.92 1.518 0.803 1.404 C0.688 1.29 0.628 1.143 0.628 0.964 C0.628 0.805 0.688 0.669 0.805 0.555 M0.696 2.173 C0.839 2.027 1.022 1.956 1.242 1.956 C1.467 1.956 1.653 2.029 1.802 2.177 C1.951 2.322 2.027 2.509 2.027 2.733 C2.027 2.954 1.954 3.137 1.809 3.279 C1.664 3.423 1.479 3.495 1.257 3.495 C1.114 3.495 0.979 3.46 0.855 3.393 C0.73 3.324 0.638 3.229 0.575 3.104 C0.51 2.979 0.48 2.85 0.48 2.718 C0.48 2.501 0.55 2.319 0.696 2.173 " xmlns="http://www.w3.org/2000/svg"/>
  </glyph>
  <glyph character="9" signature="MCCCCCCCCCCCCCLCCCCCCLCMCCCCCCCC">
    <path style="stroke-width:0.943; clip-path:url(#clipPath1); stroke-linejoin:round; stroke-linecap:round; stroke:none;" d="M0.408 3.629 C0.597 3.795 0.839 3.877 1.136 3.877 C1.416 3.877 1.66 3.8 1.869 3.652 C2.076 3.502 2.232 3.283 2.337 2.996 C2.443 2.709 2.496 2.322 2.496 1.834 C2.496 1.369 2.443 1.013 2.336 0.765 C2.231 0.519 2.074 0.33 1.87 0.197 C1.666 0.064 1.44 0.0 1.192 0.0 C0.852 0.0 0.565 0.117 0.339 0.351 C0.111 0.585 0.0 0.895 0.0 1.281 C0.0 1.654 0.108 1.955 0.324 2.181 C0.542 2.41 0.809 2.523 1.123 2.523 C1.311 2.523 1.486 2.478 1.647 2.386 C1.809 2.293 1.938 2.173 2.03 2.023 L2.033 2.117 C2.033 2.312 2.008 2.502 1.962 2.689 C1.917 2.873 1.857 3.02 1.789 3.132 C1.72 3.24 1.632 3.328 1.522 3.394 C1.416 3.46 1.291 3.496 1.147 3.496 C0.979 3.496 0.841 3.445 0.735 3.351 C0.628 3.256 0.555 3.103 0.516 2.894 L0.069 2.934 C0.106 3.231 0.22 3.464 0.408 3.629 M1.77 1.886 C1.63 2.037 1.453 2.113 1.238 2.113 C1.024 2.113 0.843 2.037 0.697 1.886 C0.552 1.734 0.477 1.539 0.477 1.298 C0.477 1.027 0.555 0.806 0.708 0.638 C0.863 0.47 1.042 0.384 1.251 0.384 C1.449 0.384 1.621 0.463 1.764 0.619 C1.906 0.779 1.978 0.99 1.978 1.257 C1.978 1.525 1.909 1.734 1.77 1.886 " xmlns="http://www.w3.org/2000/svg"/>
  </glyph>
</font>
