<dictionary title="crystal">
<entry id="" term="wavelength" name="wavelength" wikidata=""/>
<entry id="" term="spacegroup" name="spacegroup" wikidata=""/>
<entry id="" term="symmetry" name="symmetry" wikidata=""/>
<entry id="" term="P21/c" name="P21/c" wikidata=""/>
<entry id="" term="triclinic" name="triclinic" wikidata=""/>
<entry id="" term="monoclinic" name="monoclinic" wikidata="Q624543"/>
<entry id="" term="triclinic" name="triclinic" wikidata=""/>
<entry id="" term="orthorhombic" name="orthorhombic" wikidata=""/>
<entry id="" term="tetragonal" name="tetragonal" wikidata=""/>
<entry id="" term="trigonal" name="trigonal" wikidata=""/>
<entry id="" term="cubic" name="cubic" wikidata=""/>
<entry id="" term="unit cell" name="unit cell" wikidata=""/>
<entry id="" term="substance" name="substance" wikidata=""/>
<entry id="" term="sample" name="sample" wikidata=""/>
<entry id="" term="compound" name="compound" wikidata=""/>
<entry id="" term="pressure" name="pressure" wikidata=""/>
<entry id="" term="temperature" name="temperature" wikidata=""/>
</dictionary>

